Workbook
Name Slicer_AgeGroup: #N/A
Name Slicer_Department: #N/A
Name Slicer_Gender: #N/A
Name Slicer_JobRole: #N/A

Sheet Dashboard
A1: HR Analytics Dashboard
A4: Total Employees | C4: Employees Left | E4: Active Employees | G4: Attrition Rate | I4: Average Monthly Income | L4: Average Age | N4: Average Years At Company
A5: =GETPIVOTDATA("Count of EmployeeID",'KPI Pivot'!$A$3) -> 4410 | C5: =GETPIVOTDATA("Sum of AttritionFlag",'KPI Pivot'!$A$3) -> 711 | E5: =A5-C5 -> 3699 | G5: =GETPIVOTDATA("Average of AttritionFlag2",'KPI Pivot'!$A$3) -> 0.16122449 | I5: =GETPIVOTDATA("Average of MonthlyIncome",'KPI Pivot'!$A$3) -> 65029.313 | L5: =GETPIVOTDATA("Average of Age",'KPI Pivot'!$A$3) -> 36.92381 | N5: =GETPIVOTDATA("Average of YearsAtCompany",'KPI Pivot'!$A$3) -> 7.0081633

Sheet Insights
A3: HR Analytics – Key Insights
A7: • Human Resources recorded the highest attrition rate at 30.16%.
A8: • Employees under 25 had the highest attrition rate at 39.18%.
A9: • Employees with less than 2 years of tenure had an attrition rate of 34.88%.
A10: • Employees with the lowest job satisfaction had a 22.91% attrition rate, compared with 11.41% for the highest satisfaction level.
A11: • Employees with the poorest work-life balance had a 31.38% attrition rate.
A12: • Employees who left had a lower average monthly income than active employees: 61,682.62 vs 65,672.60.
A15: HR Recommendations
A18: • Focus on early-tenure retention programs, especially for employees with less than 2 years at the company.
A19: • Improve employee satisfaction and work-life balance, particularly for teams with higher attrition.
A20: • Investigate the high attrition rate in Human Resources and identify department-specific causes.
A21: • Review compensation and career development opportunities for employees at higher risk of leaving.

Sheet Analysis
A1: KPI | B1: Value
A2: Total Employees | B2: =COUNTA(tbl_HRMaster[EmployeeID]) -> 4410
A3: Employees Left | B3: =SUM(tbl_HRMaster[AttritionFlag]) -> 711
A4: Active Employees | B4: =COUNTA(tbl_HRMaster[EmployeeID])-SUM(tbl_HRMaster[AttritionFlag]) -> 3699
A5: Attrition Rate | B5: =B3/B2 -> 0.16122449
A6: Average Monthly Income | B6: =AVERAGE(tbl_HRMaster[MonthlyIncome]) -> 65029.313
A7: Average Age | B7: =AVERAGE(tbl_HRMaster[Age]) -> 36.92381
A8: Average Years at Company | B8: =AVERAGE(tbl_HRMaster[YearsAtCompany]) -> 7.0081633
A12: Department | B12: Employees Left | C12: Total Employees | D12: Attrition Rate
A13: Human Resources | B13: =COUNTIFS(tbl_HRMaster[Department],A13,tbl_HRMaster[Attrition],"Yes") -> 57 | C13: =COUNTIF(tbl_HRMaster[Department],A13) -> 189 | D13: =B13/C13 -> 0.3015873
A14: Research & Development | B14: =COUNTIFS(tbl_HRMaster[Department],A14,tbl_HRMaster[Attrition],"Yes") -> 453 | C14: =COUNTIF(tbl_HRMaster[Department],A14) -> 2883 | D14: =B14/C14 -> 0.15712799
A15: Sales | B15: =COUNTIFS(tbl_HRMaster[Department],A15,tbl_HRMaster[Attrition],"Yes") -> 201 | C15: =COUNTIF(tbl_HRMaster[Department],A15) -> 1338 | D15: =B15/C15 -> 0.15022422
A19: Employee Status | B19: Average Monthly Income
A20: Left | B20: =AVERAGEIFS(tbl_HRMaster[MonthlyIncome],tbl_HRMaster[EmployeeStatus],"Left") -> 61682.616
A21: Active | B21: =AVERAGEIFS(tbl_HRMaster[MonthlyIncome],tbl_HRMaster[EmployeeStatus],"Active") -> 65672.595
A25: Department | B25: Total Monthly Payroll
A26: Human Resources | B26: =SUMIFS(tbl_HRMaster[MonthlyIncome],tbl_HRMaster[Department],A26) -> 10943940
A27: Research & Development | B27: =SUMIFS(tbl_HRMaster[MonthlyIncome],tbl_HRMaster[Department],A27) -> 193702890
A28: Sales | B28: =SUMIFS(tbl_HRMaster[MonthlyIncome],tbl_HRMaster[Department],A28) -> 82132440

Sheet HR_Master
A1: Age | B1: Attrition | C1: BusinessTravel | D1: Department | E1: DistanceFromHome | F1: Education | G1: EducationField | H1: EmployeeID | I1: Gender | J1: JobLevel | K1: JobRole | L1: MaritalStatus | M1: MonthlyIncome | N1: NumCompaniesWorked | O1: PercentSalaryHike | P1: StockOptionLevel | Q1: TotalWorkingYears | R1: TrainingTimesLastYear | S1: YearsAtCompany | T1: YearsSinceLastPromotion | U1: YearsWithCurrManager | V1: ID_Check | W1: EnvironmentSatisfaction | X1: JobSatisfaction | Y1: WorkLifeBalance | Z1: JobInvolvement | AA1: PerformanceRating | AB1: EmployeeStatus | AC1: AgeGroup | AD1: TenureGroup | AE1: AttritionFlag
A2: 18 | B2: Yes | C2: Travel_Rarely | D2: Research & Development | E2: 1 | F2: 4 | G2: Life Sciences | H2: 39 | I2: Male | J2: 1 | K2: Sales Executive | L2: Single | M2: 23350 | N2: 1 | O2: 14 | P2: 2 | Q2: 0 | R2: 3 | S2: 0 | T2: 0 | U2: 0 | V2: =COUNTIF(tbl_HRMaster[EmployeeID],tbl_HRMaster[[#This Row],[EmployeeID]]) -> 1 | W2: =IFERROR(INDEX(tbl_EmployeeSurvey[EnvironmentSatisfaction],MATCH(tbl_HRMaster[[#This Row],[EmployeeID]],tbl_EmployeeSurvey[EmployeeID],0)),"Not Found") -> 3 | X2: =IFERROR(INDEX(tbl_EmployeeSurvey[JobSatisfaction],MATCH(tbl_HRMaster[[#This Row],[EmployeeID]],tbl_EmployeeSurvey[EmployeeID],0)),"Not Found") -> 3 | Y2: =IFERROR(INDEX(tbl_EmployeeSurvey[WorkLifeBalance],MATCH(tbl_HRMaster[[#This Row],[EmployeeID]],tbl_EmployeeSurvey[EmployeeID],0)),"Not Found") -> 3 | Z2: =IFERROR(VLOOKUP(tbl_HRMaster[[#This Row],[EmployeeID]],tbl_ManagerSurvey[[EmployeeID]:[PerformanceRating]],2,FALSE),"Not Found") -> 2 | AA2: =IFERROR(VLOOKUP(tbl_HRMaster[[#This Row],[EmployeeID]],tbl_ManagerSurvey[[EmployeeID]:[PerformanceRating]],3,FALSE),"Not Found") -> 3 | AB2: =IF(tbl_HRMaster[[#This Row],[Attrition]]="Yes","Left","Active") -> Left | AC2: =_xlfn.IFS(tbl_HRMaster[[#This Row],[Age]]<25,"Under 25",tbl_HRMaster[[#This Row],[Age]]<35,"25-34",tbl_HRMaster[[#This Row],[Age]]<45,"35-44",tbl_HRMaster[[#This Row],[Age]]<55,"45-54",TRUE,"Above 54") -> Under 25 | AD2: =_xlfn.IFS( tbl_HRMaster[[#This Row],[YearsAtCompany]]<2,"< 2 Years", tbl_HRMaster[[#This Row],[YearsAtCompany]]<5,"2-4 Years", tbl_HRMaster[[#This Row],[YearsAtCompany]]<10,"5-9 Years", TRUE,"10+ Years" ) -> < 2 Years | AE2: =IF(tbl_HRMaster[[#This Row],[Attrition]]="Yes",1,0) -> 1
A3: 18 | B3: Yes | C3: Travel_Rarely | D3: Research & Development | E3: 1 | F3: 4 | G3: Life Sciences | H3: 1509 | I3: Male | J3: 1 | K3: Sales Executive | L3: Single | M3: 23350 | N3: 1 | O3: 14 | P3: 2 | Q3: 0 | R3: 3 | S3: 0 | T3: 0 | U3: 0 | V3: =COUNTIF(tbl_HRMaster[EmployeeID],tbl_HRMaster[[#This Row],[EmployeeID]]) -> 1 | W3: =IFERROR(INDEX(tbl_EmployeeSurvey[EnvironmentSatisfaction],MATCH(tbl_HRMaster[[#This Row],[EmployeeID]],tbl_EmployeeSurvey[EmployeeID],0)),"Not Found") -> 3 | X3: =IFERROR(INDEX(tbl_EmployeeSurvey[JobSatisfaction],MATCH(tbl_HRMaster[[#This Row],[EmployeeID]],tbl_EmployeeSurvey[EmployeeID],0)),"Not Found") -> 3 | Y3: =IFERROR(INDEX(tbl_EmployeeSurvey[WorkLifeBalance],MATCH(tbl_HRMaster[[#This Row],[EmployeeID]],tbl_EmployeeSurvey[EmployeeID],0)),"Not Found") -> 3 | Z3: =IFERROR(VLOOKUP(tbl_HRMaster[[#This Row],[EmployeeID]],tbl_ManagerSurvey[[EmployeeID]:[PerformanceRating]],2,FALSE),"Not Found") -> 2 | AA3: =IFERROR(VLOOKUP(tbl_HRMaster[[#This Row],[EmployeeID]],tbl_ManagerSurvey[[EmployeeID]:[PerformanceRating]],3,FALSE),"Not Found") -> 3 | AB3: =IF(tbl_HRMaster[[#This Row],[Attrition]]="Yes","Left","Active") -> Left | AC3: =_xlfn.IFS(tbl_HRMaster[[#This Row],[Age]]<25,"Under 25",tbl_HRMaster[[#This Row],[Age]]<35,"25-34",tbl_HRMaster[[#This Row],[Age]]<45,"35-44",tbl_HRMaster[[#This Row],[Age]]<55,"45-54",TRUE,"Above 54") -> Under 25 | AD3: =_xlfn.IFS( tbl_HRMaster[[#This Row],[YearsAtCompany]]<2,"< 2 Years", tbl_HRMaster[[#This Row],[YearsAtCompany]]<5,"2-4 Years", tbl_HRMaster[[#This Row],[YearsAtCompany]]<10,"5-9 Years", TRUE,"10+ Years" ) -> < 2 Years | AE3: =IF(tbl_HRMaster[[#This Row],[Attrition]]="Yes",1,0) -> 1
A4: 18 | B4: Yes | C4: Travel_Rarely | D4: Research & Development | E4: 1 | F4: 4 | G4: Life Sciences | H4: 2979 | I4: Male | J4: 1 | K4: Sales Executive | L4: Single | M4: 23350 | N4: 1 | O4: 14 | P4: 2 | Q4: 0 | R4: 3 | S4: 0 | T4: 0 | U4: 0 | V4: =COUNTIF(tbl_HRMaster[EmployeeID],tbl_HRMaster[[#This Row],[EmployeeID]]) -> 1 | W4: =IFERROR(INDEX(tbl_EmployeeSurvey[EnvironmentSatisfaction],MATCH(tbl_HRMaster[[#This Row],[EmployeeID]],tbl_EmployeeSurvey[EmployeeID],0)),"Not Found") -> 3 | X4: =IFERROR(INDEX(tbl_EmployeeSurvey[JobSatisfaction],MATCH(tbl_HRMaster[[#This Row],[EmployeeID]],tbl_EmployeeSurvey[EmployeeID],0)),"Not Found") -> 3 | Y4: =IFERROR(INDEX(tbl_EmployeeSurvey[WorkLifeBalance],MATCH(tbl_HRMaster[[#This Row],[EmployeeID]],tbl_EmployeeSurvey[EmployeeID],0)),"Not Found") -> 3 | Z4: =IFERROR(VLOOKUP(tbl_HRMaster[[#This Row],[EmployeeID]],tbl_ManagerSurvey[[EmployeeID]:[PerformanceRating]],2,FALSE),"Not Found") -> 2 | AA4: =IFERROR(VLOOKUP(tbl_HRMaster[[#This Row],[EmployeeID]],tbl_ManagerSurvey[[EmployeeID]:[PerformanceRating]],3,FALSE),"Not Found") -> 3 | AB4: =IF(tbl_HRMaster[[#This Row],[Attrition]]="Yes","Left","Active") -> Left | AC4: =_xlfn.IFS(tbl_HRMaster[[#This Row],[Age]]<25,"Under 25",tbl_HRMaster[[#This Row],[Age]]<35,"25-34",tbl_HRMaster[[#This Row],[Age]]<45,"35-44",tbl_HRMaster[[#This Row],[Age]]<55,"45-54",TRUE,"Above 54") -> Under 25 | AD4: =_xlfn.IFS( tbl_HRMaster[[#This Row],[YearsAtCompany]]<2,"< 2 Years", tbl_HRMaster[[#This Row],[YearsAtCompany]]<5,"2-4 Years", tbl_HRMaster[[#This Row],[YearsAtCompany]]<10,"5-9 Years", TRUE,"10+ Years" ) -> < 2 Years | AE4: =IF(tbl_HRMaster[[#This Row],[Attrition]]="Yes",1,0) -> 1
A5: 18 | B5: Yes | C5: Travel_Frequently | D5: Research & Development | E5: 3 | F5: 5 | G5: Medical | H5: 896 | I5: Male | J5: 1 | K5: Research Director | L5: Single | M5: 24790 | N5: 1 | O5: 12 | P5: 1 | Q5: 0 | R5: 2 | S5: 0 | T5: 0 | U5: 0 | V5: =COUNTIF(tbl_HRMaster[EmployeeID],tbl_HRMaster[[#This Row],[EmployeeID]]) -> 1 | W5: =IFERROR(INDEX(tbl_EmployeeSurvey[EnvironmentSatisfaction],MATCH(tbl_HRMaster[[#This Row],[EmployeeID]],tbl_EmployeeSurvey[EmployeeID],0)),"Not Found") -> 2 | X5: =IFERROR(INDEX(tbl_EmployeeSurvey[JobSatisfaction],MATCH(tbl_HRMaster[[#This Row],[EmployeeID]],tbl_EmployeeSurvey[EmployeeID],0)),"Not Found") -> 4 | Y5: =IFERROR(INDEX(tbl_EmployeeSurvey[WorkLifeBalance],MATCH(tbl_HRMaster[[#This Row],[EmployeeID]],tbl_EmployeeSurvey[EmployeeID],0)),"Not Found") -> 4 | Z5: =IFERROR(VLOOKUP(tbl_HRMaster[[#This Row],[EmployeeID]],tbl_ManagerSurvey[[EmployeeID]:[PerformanceRating]],2,FALSE),"Not Found") -> 2 | AA5: =IFERROR(VLOOKUP(tbl_HRMaster[[#This Row],[EmployeeID]],tbl_ManagerSurvey[[EmployeeID]:[PerformanceRating]],3,FALSE),"Not Found") -> 3 | AB5: =IF(tbl_HRMaster[[#This Row],[Attrition]]="Yes","Left","Active") -> Left | AC5: =_xlfn.IFS(tbl_HRMaster[[#This Row],[Age]]<25,"Under 25",tbl_HRMaster[[#This Row],[Age]]<35,"25-34",tbl_HRMaster[[#This Row],[Age]]<45,"35-44",tbl_HRMaster[[#This Row],[Age]]<55,"45-54",TRUE,"Above 54") -> Under 25 | AD5: =_xlfn.IFS( tbl_HRMaster[[#This Row],[YearsAtCompany]]<2,"< 2 Years", tbl_HRMaster[[#This Row],[YearsAtCompany]]<5,"2-4 Years", tbl_HRMaster[[#This Row],[YearsAtCompany]]<10,"5-9 Years", TRUE,"10+ Years" ) -> < 2 Years | AE5: =IF(tbl_HRMaster[[#This Row],[Attrition]]="Yes",1,0) -> 1
A6: 18 | B6: Yes | C6: Travel_Frequently | D6: Research & Development | E6: 3 | F6: 5 | G6: Medical | H6: 2366 | I6: Male | J6: 1 | K6: Research Director | L6: Single | M6: 24790 | N6: 2 | O6: 12 | P6: 1 | Q6: 0 | R6: 2 | S6: 0 | T6: 0 | U6: 0 | V6: =COUNTIF(tbl_HRMaster[EmployeeID],tbl_HRMaster[[#This Row],[EmployeeID]]) -> 1 | W6: =IFERROR(INDEX(tbl_EmployeeSurvey[EnvironmentSatisfaction],MATCH(tbl_HRMaster[[#This Row],[EmployeeID]],tbl_EmployeeSurvey[EmployeeID],0)),"Not Found") -> 2 | X6: =IFERROR(INDEX(tbl_EmployeeSurvey[JobSatisfaction],MATCH(tbl_HRMaster[[#This Row],[EmployeeID]],tbl_EmployeeSurvey[EmployeeID],0)),"Not Found") -> 4 | Y6: =IFERROR(INDEX(tbl_EmployeeSurvey[WorkLifeBalance],MATCH(tbl_HRMaster[[#This Row],[EmployeeID]],tbl_EmployeeSurvey[EmployeeID],0)),"Not Found") -> 4 | Z6: =IFERROR(VLOOKUP(tbl_HRMaster[[#This Row],[EmployeeID]],tbl_ManagerSurvey[[EmployeeID]:[PerformanceRating]],2,FALSE),"Not Found") -> 2 | AA6: =IFERROR(VLOOKUP(tbl_HRMaster[[#This Row],[EmployeeID]],tbl_ManagerSurvey[[EmployeeID]:[PerformanceRating]],3,FALSE),"Not Found") -> 3 | AB6: =IF(tbl_HRMaster[[#This Row],[Attrition]]="Yes","Left","Active") -> Left | AC6: =_xlfn.IFS(tbl_HRMaster[[#This Row],[Age]]<25,"Under 25",tbl_HRMaster[[#This Row],[Age]]<35,"25-34",tbl_HRMaster[[#This Row],[Age]]<45,"35-44",tbl_HRMaster[[#This Row],[Age]]<55,"45-54",TRUE,"Above 54") -> Under 25 | AD6: =_xlfn.IFS( tbl_HRMaster[[#This Row],[YearsAtCompany]]<2,"< 2 Years", tbl_HRMaster[[#This Row],[YearsAtCompany]]<5,"2-4 Years", tbl_HRMaster[[#This Row],[YearsAtCompany]]<10,"5-9 Years", TRUE,"10+ Years" ) -> < 2 Years | AE6: =IF(tbl_HRMaster[[#This Row],[Attrition]]="Yes",1,0) -> 1
A7: 18 | B7: Yes | C7: Travel_Frequently | D7: Research & Development | E7: 3 | F7: 5 | G7: Medical | H7: 3836 | I7: Male | J7: 1 | K7: Research Director | L7: Single | M7: 24790 | N7: 1 | O7: 12 | P7: 1 | Q7: 0 | R7: 2 | S7: 0 | T7: 0 | U7: 0 | V7: =COUNTIF(tbl_HRMaster[EmployeeID],tbl_HRMaster[[#This Row],[EmployeeID]]) -> 1 | W7: =IFERROR(INDEX(tbl_EmployeeSurvey[EnvironmentSatisfaction],MATCH(tbl_HRMaster[[#This Row],[EmployeeID]],tbl_EmployeeSurvey[EmployeeID],0)),"Not Found") -> 2 | X7: =IFERROR(INDEX(tbl_EmployeeSurvey[JobSatisfaction],MATCH(tbl_HRMaster[[#This Row],[EmployeeID]],tbl_EmployeeSurvey[EmployeeID],0)),"Not Found") -> 4 | Y7: =IFERROR(INDEX(tbl_EmployeeSurvey[WorkLifeBalance],MATCH(tbl_HRMaster[[#This Row],[EmployeeID]],tbl_EmployeeSurvey[EmployeeID],0)),"Not Found") -> 4 | Z7: =IFERROR(VLOOKUP(tbl_HRMaster[[#This Row],[EmployeeID]],tbl_ManagerSurvey[[EmployeeID]:[PerformanceRating]],2,FALSE),"Not Found") -> 2 | AA7: =IFERROR(VLOOKUP(tbl_HRMaster[[#This Row],[EmployeeID]],tbl_ManagerSurvey[[EmployeeID]:[PerformanceRating]],3,FALSE),"Not Found") -> 3 | AB7: =IF(tbl_HRMaster[[#This Row],[Attrition]]="Yes","Left","Active") -> Left | AC7: =_xlfn.IFS(tbl_HRMaster[[#This Row],[Age]]<25,"Under 25",tbl_HRMaster[[#This Row],[Age]]<35,"25-34",tbl_HRMaster[[#This Row],[Age]]<45,"35-44",tbl_HRMaster[[#This Row],[Age]]<55,"45-54",TRUE,"Above 54") -> Under 25 | AD7: =_xlfn.IFS( tbl_HRMaster[[#This Row],[YearsAtCompany]]<2,"< 2 Years", tbl_HRMaster[[#This Row],[YearsAtCompany]]<5,"2-4 Years", tbl_HRMaster[[#This Row],[YearsAtCompany]]<10,"5-9 Years", TRUE,"10+ Years" ) -> < 2 Years | AE7: =IF(tbl_HRMaster[[#This Row],[Attrition]]="Yes",1,0) -> 1
A8: 27 | B8: No | C8: Non-Travel | D8: Sales | E8: 1 | F8: 3 | G8: Technical Degree | H8: 358 | I8: Female | J8: 1 | K8: Sales Executive | L8: Married | M8: 27130 | N8: 1 | O8: 11 | P8: 0 | Q8: 0 | R8: 2 | S8: 0 | T8: 0 | U8: 0 | V8: =COUNTIF(tbl_HRMaster[EmployeeID],tbl_HRMaster[[#This Row],[EmployeeID]]) -> 1 | W8: =IFERROR(INDEX(tbl_EmployeeSurvey[EnvironmentSatisfaction],MATCH(tbl_HRMaster[[#This Row],[EmployeeID]],tbl_EmployeeSurvey[EmployeeID],0)),"Not Found") -> 4 | X8: =IFERROR(INDEX(tbl_EmployeeSurvey[JobSatisfaction],MATCH(tbl_HRMaster[[#This Row],[EmployeeID]],tbl_EmployeeSurvey[EmployeeID],0)),"Not Found") -> 4 | Y8: =IFERROR(INDEX(tbl_EmployeeSurvey[WorkLifeBalance],MATCH(tbl_HRMaster[[#This Row],[EmployeeID]],tbl_EmployeeSurvey[EmployeeID],0)),"Not Found") -> 2 | Z8: =IFERROR(VLOOKUP(tbl_HRMaster[[#This Row],[EmployeeID]],tbl_ManagerSurvey[[EmployeeID]:[PerformanceRating]],2,FALSE),"Not Found") -> 3 | AA8: =IFERROR(VLOOKUP(tbl_HRMaster[[#This Row],[EmployeeID]],tbl_ManagerSurvey[[EmployeeID]:[PerformanceRating]],3,FALSE),"Not Found") -> 3 | AB8: =IF(tbl_HRMaster[[#This Row],[Attrition]]="Yes","Left","Active") -> Active | AC8: =_xlfn.IFS(tbl_HRMaster[[#This Row],[Age]]<25,"Under 25",tbl_HRMaster[[#This Row],[Age]]<35,"25-34",tbl_HRMaster[[#This Row],[Age]]<45,"35-44",tbl_HRMaster[[#This Row],[Age]]<55,"45-54",TRUE,"Above 54") -> 25-34 | AD8: =_xlfn.IFS( tbl_HRMaster[[#This Row],[YearsAtCompany]]<2,"< 2 Years", tbl_HRMaster[[#This Row],[YearsAtCompany]]<5,"2-4 Years", tbl_HRMaster[[#This Row],[YearsAtCompany]]<10,"5-9 Years", TRUE,"10+ Years" ) -> < 2 Years | AE8: =IF(tbl_HRMaster[[#This Row],[Attrition]]="Yes",1,0) -> 0
A9: 27 | B9: No | C9: Non-Travel | D9: Sales | E9: 1 | F9: 3 | G9: Technical Degree | H9: 1828 | I9: Female | J9: 1 | K9: Sales Executive | L9: Married | M9: 27130 | N9: 1 | O9: 11 | P9: 0 | Q9: 0 | R9: 2 | S9: 0 | T9: 0 | U9: 0 | V9: =COUNTIF(tbl_HRMaster[EmployeeID],tbl_HRMaster[[#This Row],[EmployeeID]]) -> 1 | W9: =IFERROR(INDEX(tbl_EmployeeSurvey[EnvironmentSatisfaction],MATCH(tbl_HRMaster[[#This Row],[EmployeeID]],tbl_EmployeeSurvey[EmployeeID],0)),"Not Found") -> 4 | X9: =IFERROR(INDEX(tbl_EmployeeSurvey[JobSatisfaction],MATCH(tbl_HRMaster[[#This Row],[EmployeeID]],tbl_EmployeeSurvey[EmployeeID],0)),"Not Found") -> 4 | Y9: =IFERROR(INDEX(tbl_EmployeeSurvey[WorkLifeBalance],MATCH(tbl_HRMaster[[#This Row],[EmployeeID]],tbl_EmployeeSurvey[EmployeeID],0)),"Not Found") -> 2 | Z9: =IFERROR(VLOOKUP(tbl_HRMaster[[#This Row],[EmployeeID]],tbl_ManagerSurvey[[EmployeeID]:[PerformanceRating]],2,FALSE),"Not Found") -> 3 | AA9: =IFERROR(VLOOKUP(tbl_HRMaster[[#This Row],[EmployeeID]],tbl_ManagerSurvey[[EmployeeID]:[PerformanceRating]],3,FALSE),"Not Found") -> 3 | AB9: =IF(tbl_HRMaster[[#This Row],[Attrition]]="Yes","Left","Active") -> Active | AC9: =_xlfn.IFS(tbl_HRMaster[[#This Row],[Age]]<25,"Under 25",tbl_HRMaster[[#This Row],[Age]]<35,"25-34",tbl_HRMaster[[#This Row],[Age]]<45,"35-44",tbl_HRMaster[[#This Row],[Age]]<55,"45-54",TRUE,"Above 54") -> 25-34 | AD9: =_xlfn.IFS( tbl_HRMaster[[#This Row],[YearsAtCompany]]<2,"< 2 Years", tbl_HRMaster[[#This Row],[YearsAtCompany]]<5,"2-4 Years", tbl_HRMaster[[#This Row],[YearsAtCompany]]<10,"5-9 Years", TRUE,"10+ Years" ) -> < 2 Years | AE9: =IF(tbl_HRMaster[[#This Row],[Attrition]]="Yes",1,0) -> 0
A10: 27 | B10: No | C10: Non-Travel | D10: Sales | E10: 1 | F10: 3 | G10: Technical Degree | H10: 3298 | I10: Female | J10: 1 | K10: Sales Executive | L10: Married | M10: 27130 | N10: 1 | O10: 11 | P10: 0 | Q10: 0 | R10: 2 | S10: 0 | T10: 0 | U10: 0 | V10: =COUNTIF(tbl_HRMaster[EmployeeID],tbl_HRMaster[[#This Row],[EmployeeID]]) -> 1 | W10: =IFERROR(INDEX(tbl_EmployeeSurvey[EnvironmentSatisfaction],MATCH(tbl_HRMaster[[#This Row],[EmployeeID]],tbl_EmployeeSurvey[EmployeeID],0)),"Not Found") -> 4 | X10: =IFERROR(INDEX(tbl_EmployeeSurvey[JobSatisfaction],MATCH(tbl_HRMaster[[#This Row],[EmployeeID]],tbl_EmployeeSurvey[EmployeeID],0)),"Not Found") -> 4 | Y10: =IFERROR(INDEX(tbl_EmployeeSurvey[WorkLifeBalance],MATCH(tbl_HRMaster[[#This Row],[EmployeeID]],tbl_EmployeeSurvey[EmployeeID],0)),"Not Found") -> 2 | Z10: =IFERROR(VLOOKUP(tbl_HRMaster[[#This Row],[EmployeeID]],tbl_ManagerSurvey[[EmployeeID]:[PerformanceRating]],2,FALSE),"Not Found") -> 3 | AA10: =IFERROR(VLOOKUP(tbl_HRMaster[[#This Row],[EmployeeID]],tbl_ManagerSurvey[[EmployeeID]:[PerformanceRating]],3,FALSE),"Not Found") -> 3 | AB10: =IF(tbl_HRMaster[[#This Row],[Attrition]]="Yes","Left","Active") -> Active | AC10: =_xlfn.IFS(tbl_HRMaster[[#This Row],[Age]]<25,"Under 25",tbl_HRMaster[[#This Row],[Age]]<35,"25-34",tbl_HRMaster[[#This Row],[Age]]<45,"35-44",tbl_HRMaster[[#This Row],[Age]]<55,"45-54",TRUE,"Above 54") -> 25-34 | AD10: =_xlfn.IFS( tbl_HRMaster[[#This Row],[YearsAtCompany]]<2,"< 2 Years", tbl_HRMaster[[#This Row],[YearsAtCompany]]<5,"2-4 Years", tbl_HRMaster[[#This Row],[YearsAtCompany]]<10,"5-9 Years", TRUE,"10+ Years" ) -> < 2 Years | AE10: =IF(tbl_HRMaster[[#This Row],[Attrition]]="Yes",1,0) -> 0
A11: 18 | B11: No | C11: Non-Travel | D11: Research & Development | E11: 1 | F11: 4 | G11: Medical | H11: 715 | I11: Male | J11: 2 | K11: Sales Executive | L11: Single | M11: 27200 | N11: 1 | O11: 22 | P11: 1 | Q11: 0 | R11: 2 | S11: 0 | T11: 0 | U11: 0 | V11: =COUNTIF(tbl_HRMaster[EmployeeID],tbl_HRMaster[[#This Row],[EmployeeID]]) -> 1 | W11: =IFERROR(INDEX(tbl_EmployeeSurvey[EnvironmentSatisfaction],MATCH(tbl_HRMaster[[#This Row],[EmployeeID]],tbl_EmployeeSurvey[EmployeeID],0)),"Not Found") -> 4 | X11: =IFERROR(INDEX(tbl_EmployeeSurvey[JobSatisfaction],MATCH(tbl_HRMaster[[#This Row],[EmployeeID]],tbl_EmployeeSurvey[EmployeeID],0)),"Not Found") -> 4 | Y11: =IFERROR(INDEX(tbl_EmployeeSurvey[WorkLifeBalance],MATCH(tbl_HRMaster[[#This Row],[EmployeeID]],tbl_EmployeeSurvey[EmployeeID],0)),"Not Found") -> 4 | Z11: =IFERROR(VLOOKUP(tbl_HRMaster[[#This Row],[EmployeeID]],tbl_ManagerSurvey[[EmployeeID]:[PerformanceRating]],2,FALSE),"Not Found") -> 3 | AA11: =IFERROR(VLOOKUP(tbl_HRMaster[[#This Row],[EmployeeID]],tbl_ManagerSurvey[[EmployeeID]:[PerformanceRating]],3,FALSE),"Not Found") -> 4 | AB11: =IF(tbl_HRMaster[[#This Row],[Attrition]]="Yes","Left","Active") -> Active | AC11: =_xlfn.IFS(tbl_HRMaster[[#This Row],[Age]]<25,"Under 25",tbl_HRMaster[[#This Row],[Age]]<35,"25-34",tbl_HRMaster[[#This Row],[Age]]<45,"35-44",tbl_HRMaster[[#This Row],[Age]]<55,"45-54",TRUE,"Above 54") -> Under 25 | AD11: =_xlfn.IFS( tbl_HRMaster[[#This Row],[YearsAtCompany]]<2,"< 2 Years", tbl_HRMaster[[#This Row],[YearsAtCompany]]<5,"2-4 Years", tbl_HRMaster[[#This Row],[YearsAtCompany]]<10,"5-9 Years", TRUE,"10+ Years" ) -> < 2 Years | AE11: =IF(tbl_HRMaster[[#This Row],[Attrition]]="Yes",1,0) -> 0
A12: 18 | B12: No | C12: Non-Travel | D12: Research & Development | E12: 1 | F12: 4 | G12: Medical | H12: 2185 | I12: Male | J12: 2 | K12: Sales Executive | L12: Single | M12: 27200 | N12: 1 | O12: 22 | P12: 1 | Q12: 0 | R12: 2 | S12: 0 | T12: 0 | U12: 0 | V12: =COUNTIF(tbl_HRMaster[EmployeeID],tbl_HRMaster[[#This Row],[EmployeeID]]) -> 1 | W12: =IFERROR(INDEX(tbl_EmployeeSurvey[EnvironmentSatisfaction],MATCH(tbl_HRMaster[[#This Row],[EmployeeID]],tbl_EmployeeSurvey[EmployeeID],0)),"Not Found") -> 4 | X12: =IFERROR(INDEX(tbl_EmployeeSurvey[JobSatisfaction],MATCH(tbl_HRMaster[[#This Row],[EmployeeID]],tbl_EmployeeSurvey[EmployeeID],0)),"Not Found") -> 4 | Y12: =IFERROR(INDEX(tbl_EmployeeSurvey[WorkLifeBalance],MATCH(tbl_HRMaster[[#This Row],[EmployeeID]],tbl_EmployeeSurvey[EmployeeID],0)),"Not Found") -> 4 | Z12: =IFERROR(VLOOKUP(tbl_HRMaster[[#This Row],[EmployeeID]],tbl_ManagerSurvey[[EmployeeID]:[PerformanceRating]],2,FALSE),"Not Found") -> 3 | AA12: =IFERROR(VLOOKUP(tbl_HRMaster[[#This Row],[EmployeeID]],tbl_ManagerSurvey[[EmployeeID]:[PerformanceRating]],3,FALSE),"Not Found") -> 4 | AB12: =IF(tbl_HRMaster[[#This Row],[Attrition]]="Yes","Left","Active") -> Active | AC12: =_xlfn.IFS(tbl_HRMaster[[#This Row],[Age]]<25,"Under 25",tbl_HRMaster[[#This Row],[Age]]<35,"25-34",tbl_HRMaster[[#This Row],[Age]]<45,"35-44",tbl_HRMaster[[#This Row],[Age]]<55,"45-54",TRUE,"Above 54") -> Under 25 | AD12: =_xlfn.IFS( tbl_HRMaster[[#This Row],[YearsAtCompany]]<2,"< 2 Years", tbl_HRMaster[[#This Row],[YearsAtCompany]]<5,"2-4 Years", tbl_HRMaster[[#This Row],[YearsAtCompany]]<10,"5-9 Years", TRUE,"10+ Years" ) -> < 2 Years | AE12: =IF(tbl_HRMaster[[#This Row],[Attrition]]="Yes",1,0) -> 0
A13: 18 | B13: No | C13: Non-Travel | D13: Research & Development | E13: 1 | F13: 4 | G13: Medical | H13: 3655 | I13: Male | J13: 2 | K13: Sales Executive | L13: Single | M13: 27200 | N13: 1 | O13: 22 | P13: 1 | Q13: 0 | R13: 2 | S13: 0 | T13: 0 | U13: 0 | V13: =COUNTIF(tbl_HRMaster[EmployeeID],tbl_HRMaster[[#This Row],[EmployeeID]]) -> 1 | W13: =IFERROR(INDEX(tbl_EmployeeSurvey[EnvironmentSatisfaction],MATCH(tbl_HRMaster[[#This Row],[EmployeeID]],tbl_EmployeeSurvey[EmployeeID],0)),"Not Found") -> 4 | X13: =IFERROR(INDEX(tbl_EmployeeSurvey[JobSatisfaction],MATCH(tbl_HRMaster[[#This Row],[EmployeeID]],tbl_EmployeeSurvey[EmployeeID],0)),"Not Found") -> 4 | Y13: =IFERROR(INDEX(tbl_EmployeeSurvey[WorkLifeBalance],MATCH(tbl_HRMaster[[#This Row],[EmployeeID]],tbl_EmployeeSurvey[EmployeeID],0)),"Not Found") -> 3 | Z13: =IFERROR(VLOOKUP(tbl_HRMaster[[#This Row],[EmployeeID]],tbl_ManagerSurvey[[EmployeeID]:[PerformanceRating]],2,FALSE),"Not Found") -> 3 | AA13: =IFERROR(VLOOKUP(tbl_HRMaster[[#This Row],[EmployeeID]],tbl_ManagerSurvey[[EmployeeID]:[PerformanceRating]],3,FALSE),"Not Found") -> 4 | AB13: =IF(tbl_HRMaster[[#This Row],[Attrition]]="Yes","Left","Active") -> Active | AC13: =_xlfn.IFS(tbl_HRMaster[[#This Row],[Age]]<25,"Under 25",tbl_HRMaster[[#This Row],[Age]]<35,"25-34",tbl_HRMaster[[#This Row],[Age]]<45,"35-44",tbl_HRMaster[[#This Row],[Age]]<55,"45-54",TRUE,"Above 54") -> Under 25 | AD13: =_xlfn.IFS( tbl_HRMaster[[#This Row],[YearsAtCompany]]<2,"< 2 Years", tbl_HRMaster[[#This Row],[YearsAtCompany]]<5,"2-4 Years", tbl_HRMaster[[#This Row],[YearsAtCompany]]<10,"5-9 Years", TRUE,"10+ Years" ) -> < 2 Years | AE13: =IF(tbl_HRMaster[[#This Row],[Attrition]]="Yes",1,0) -> 0
... A4411: 58 | B4411: Yes | C4411: Travel_Rarely | D4411: Sales | E4411: 2 | F4411: 2 | G4411: Medical | H4411: 4279 | I4411: Female | J4411: 1 | K4411: Research Scientist | L4411: Married | M4411: 43850 | N4411: 1 | O4411: 13 | P4411: 1 | Q4411: 40 | R4411: 2 | S4411: 40 | T4411: 15 | U4411: 6 | V4411: =COUNTIF(tbl_HRMaster[EmployeeID],tbl_HRMaster[[#This Row],[EmployeeID]]) -> 1 | W4411: =IFERROR(INDEX(tbl_EmployeeSurvey[EnvironmentSatisfaction],MATCH(tbl_HRMaster[[#This Row],[EmployeeID]],tbl_EmployeeSurvey[EmployeeID],0)),"Not Found") -> 4 | X4411: =IFERROR(INDEX(tbl_EmployeeSurvey[JobSatisfaction],MATCH(tbl_HRMaster[[#This Row],[EmployeeID]],tbl_EmployeeSurvey[EmployeeID],0)),"Not Found") -> 4 | Y4411: =IFERROR(INDEX(tbl_EmployeeSurvey[WorkLifeBalance],MATCH(tbl_HRMaster[[#This Row],[EmployeeID]],tbl_EmployeeSurvey[EmployeeID],0)),"Not Found") -> 2 | Z4411: =IFERROR(VLOOKUP(tbl_HRMaster[[#This Row],[EmployeeID]],tbl_ManagerSurvey[[EmployeeID]:[PerformanceRating]],2,FALSE),"Not Found") -> 2 | AA4411: =IFERROR(VLOOKUP(tbl_HRMaster[[#This Row],[EmployeeID]],tbl_ManagerSurvey[[EmployeeID]:[PerformanceRating]],3,FALSE),"Not Found") -> 3 | AB4411: =IF(tbl_HRMaster[[#This Row],[Attrition]]="Yes","Left","Active") -> Left | AC4411: =_xlfn.IFS(tbl_HRMaster[[#This Row],[Age]]<25,"Under 25",tbl_HRMaster[[#This Row],[Age]]<35,"25-34",tbl_HRMaster[[#This Row],[Age]]<45,"35-44",tbl_HRMaster[[#This Row],[Age]]<55,"45-54",TRUE,"Above 54") -> Above 54 | AD4411: =_xlfn.IFS( tbl_HRMaster[[#This Row],[YearsAtCompany]]<2,"< 2 Years", tbl_HRMaster[[#This Row],[YearsAtCompany]]<5,"2-4 Years", tbl_HRMaster[[#This Row],[YearsAtCompany]]<10,"5-9 Years", TRUE,"10+ Years" ) -> 10+ Years | AE4411: =IF(tbl_HRMaster[[#This Row],[Attrition]]="Yes",1,0) -> 1

Sheet Data_Quality_General
A1: Data_Quality | B1: Age | C1: Department | D1: JobRole | E1: MonthlyIncome | F1: NumCompaniesWorked | G1: TotalWorkingYears | H1: YearsAtCompany | I1: YearsSinceLastPromotion | J1: YearsWithCurrManager
A2: Blank Count | B2: =COUNTBLANK(tbl_General[Age]) -> 0 | C2: =COUNTBLANK(tbl_General[Department]) -> 0 | D2: =COUNTBLANK(tbl_General[JobRole]) -> 0 | E2: =COUNTBLANK(tbl_General[MonthlyIncome]) -> 0 | F2: =COUNTBLANK(tbl_General[NumCompaniesWorked]) -> 0 | G2: =COUNTBLANK(tbl_General[TotalWorkingYears]) -> 0 | H2: =COUNTBLANK(tbl_General[YearsAtCompany]) -> 0 | I2: =COUNTBLANK(tbl_General[YearsSinceLastPromotion]) -> 0 | J2: =COUNTBLANK(tbl_General[YearsWithCurrManager]) -> 0
A3: NA Count | B3: 0 | C3: 0 | D3: 0 | E3: 0 | F3: =COUNTIF(tbl_General[NumCompaniesWorked],"NA") -> 0 | G3: =COUNTIF(tbl_General[TotalWorkingYears],"NA") -> 0 | H3: 0 | I3: 0 | J3: 0
A4: Median | B4: 0 | C4: 0 | D4: 0 | E4: 0 | F4: =MEDIAN(tbl_General[NumCompaniesWorked]) -> 2 | G4: =MEDIAN(tbl_General[TotalWorkingYears]) -> 10 | H4: 0 | I4: 0 | J4: 0

Sheet Data_Quality_EmployeeSurvey
A1: Check | B1: EnvironmentSatisfaction | C1: JobSatisfaction | D1: WorkLifeBalance
A2: Blank Count | B2: =COUNTBLANK([1]!tbl_EmployeeSurvey[EnvironmentSatisfaction]) -> 0 | C2: =COUNTBLANK([1]!tbl_EmployeeSurvey[JobSatisfaction]) -> 0 | D2: =COUNTBLANK([1]!tbl_EmployeeSurvey[WorkLifeBalance]) -> 0
A3: NA Count | B3: =COUNTIF([1]!tbl_EmployeeSurvey[EnvironmentSatisfaction],"NA") -> 0 | C3: =COUNTIF([1]!tbl_EmployeeSurvey[JobSatisfaction],"NA") -> 0 | D3: =COUNTIF([1]!tbl_EmployeeSurvey[WorkLifeBalance],"NA") -> 0
A4: Min | B4: =MIN([1]!tbl_EmployeeSurvey[EnvironmentSatisfaction]) -> 1 | C4: =MIN([1]!tbl_EmployeeSurvey[JobSatisfaction]) -> 1 | D4: =MIN([1]!tbl_EmployeeSurvey[WorkLifeBalance]) -> 1
A5: Max | B5: =MAX([1]!tbl_EmployeeSurvey[EnvironmentSatisfaction]) -> 4 | C5: =MAX([1]!tbl_EmployeeSurvey[JobSatisfaction]) -> 4 | D5: =MAX([1]!tbl_EmployeeSurvey[WorkLifeBalance]) -> 4
A6: Median | B6: =MEDIAN([1]!tbl_EmployeeSurvey[EnvironmentSatisfaction]) -> 3 | C6: =MEDIAN([1]!tbl_EmployeeSurvey[JobSatisfaction]) -> 3 | D6: =MEDIAN([1]!tbl_EmployeeSurvey[WorkLifeBalance]) -> 3

Sheet Data_Quality_ManagerSurvey
A1: Check | B1: JobInvolvement | C1: PerformanceRating
A2: Blank Count | B2: =COUNTBLANK([2]!tbl_ManagerSurvey[JobInvolvement]) -> 0 | C2: =COUNTBLANK([2]!tbl_ManagerSurvey[PerformanceRating]) -> 0
A3: NA Count | B3: =COUNTIF([2]!tbl_ManagerSurvey[JobInvolvement],"NA") -> 0 | C3: =COUNTIF([2]!tbl_ManagerSurvey[PerformanceRating],"NA") -> 0
A4: Min | B4: =MIN([2]!tbl_ManagerSurvey[JobInvolvement]) -> 1 | C4: =MIN([2]!tbl_ManagerSurvey[PerformanceRating]) -> 3
A5: Max | B5: =MAX([2]!tbl_ManagerSurvey[JobInvolvement]) -> 4 | C5: =MAX([2]!tbl_ManagerSurvey[PerformanceRating]) -> 4
A6: Median | B6: =MEDIAN([2]!tbl_ManagerSurvey[JobInvolvement]) -> 3 | C6: =MEDIAN([2]!tbl_ManagerSurvey[PerformanceRating]) -> 3

Sheet general_data
A1: Age | B1: Attrition | C1: BusinessTravel | D1: Department | E1: DistanceFromHome | F1: Education | G1: EducationField | H1: EmployeeID | I1: Gender | J1: JobLevel | K1: JobRole | L1: MaritalStatus | M1: MonthlyIncome | N1: NumCompaniesWorked | O1: PercentSalaryHike | P1: StockOptionLevel | Q1: TotalWorkingYears | R1: TrainingTimesLastYear | S1: YearsAtCompany | T1: YearsSinceLastPromotion | U1: YearsWithCurrManager | V1: ID_Check
A2: 18 | B2: Yes | C2: Travel_Rarely | D2: Research & Development | E2: 1 | F2: 4 | G2: Life Sciences | H2: 39 | I2: Male | J2: 1 | K2: Sales Executive | L2: Single | M2: 23350 | N2: 1 | O2: 14 | P2: 2 | Q2: 0 | R2: 3 | S2: 0 | T2: 0 | U2: 0 | V2: =COUNTIF(tbl_General[EmployeeID],tbl_General[[#This Row],[EmployeeID]]) -> 1
A3: 18 | B3: Yes | C3: Travel_Rarely | D3: Research & Development | E3: 1 | F3: 4 | G3: Life Sciences | H3: 1509 | I3: Male | J3: 1 | K3: Sales Executive | L3: Single | M3: 23350 | N3: 1 | O3: 14 | P3: 2 | Q3: 0 | R3: 3 | S3: 0 | T3: 0 | U3: 0 | V3: =COUNTIF(tbl_General[EmployeeID],tbl_General[[#This Row],[EmployeeID]]) -> 1
A4: 18 | B4: Yes | C4: Travel_Rarely | D4: Research & Development | E4: 1 | F4: 4 | G4: Life Sciences | H4: 2979 | I4: Male | J4: 1 | K4: Sales Executive | L4: Single | M4: 23350 | N4: 1 | O4: 14 | P4: 2 | Q4: 0 | R4: 3 | S4: 0 | T4: 0 | U4: 0 | V4: =COUNTIF(tbl_General[EmployeeID],tbl_General[[#This Row],[EmployeeID]]) -> 1
A5: 18 | B5: Yes | C5: Travel_Frequently | D5: Research & Development | E5: 3 | F5: 5 | G5: Medical | H5: 896 | I5: Male | J5: 1 | K5: Research Director | L5: Single | M5: 24790 | N5: 1 | O5: 12 | P5: 1 | Q5: 0 | R5: 2 | S5: 0 | T5: 0 | U5: 0 | V5: =COUNTIF(tbl_General[EmployeeID],tbl_General[[#This Row],[EmployeeID]]) -> 1
A6: 18 | B6: Yes | C6: Travel_Frequently | D6: Research & Development | E6: 3 | F6: 5 | G6: Medical | H6: 2366 | I6: Male | J6: 1 | K6: Research Director | L6: Single | M6: 24790 | N6: 2 | O6: 12 | P6: 1 | Q6: 0 | R6: 2 | S6: 0 | T6: 0 | U6: 0 | V6: =COUNTIF(tbl_General[EmployeeID],tbl_General[[#This Row],[EmployeeID]]) -> 1
A7: 18 | B7: Yes | C7: Travel_Frequently | D7: Research & Development | E7: 3 | F7: 5 | G7: Medical | H7: 3836 | I7: Male | J7: 1 | K7: Research Director | L7: Single | M7: 24790 | N7: 1 | O7: 12 | P7: 1 | Q7: 0 | R7: 2 | S7: 0 | T7: 0 | U7: 0 | V7: =COUNTIF(tbl_General[EmployeeID],tbl_General[[#This Row],[EmployeeID]]) -> 1
A8: 27 | B8: No | C8: Non-Travel | D8: Sales | E8: 1 | F8: 3 | G8: Technical Degree | H8: 358 | I8: Female | J8: 1 | K8: Sales Executive | L8: Married | M8: 27130 | N8: 1 | O8: 11 | P8: 0 | Q8: 0 | R8: 2 | S8: 0 | T8: 0 | U8: 0 | V8: =COUNTIF(tbl_General[EmployeeID],tbl_General[[#This Row],[EmployeeID]]) -> 1
A9: 27 | B9: No | C9: Non-Travel | D9: Sales | E9: 1 | F9: 3 | G9: Technical Degree | H9: 1828 | I9: Female | J9: 1 | K9: Sales Executive | L9: Married | M9: 27130 | N9: 1 | O9: 11 | P9: 0 | Q9: 0 | R9: 2 | S9: 0 | T9: 0 | U9: 0 | V9: =COUNTIF(tbl_General[EmployeeID],tbl_General[[#This Row],[EmployeeID]]) -> 1
A10: 27 | B10: No | C10: Non-Travel | D10: Sales | E10: 1 | F10: 3 | G10: Technical Degree | H10: 3298 | I10: Female | J10: 1 | K10: Sales Executive | L10: Married | M10: 27130 | N10: 1 | O10: 11 | P10: 0 | Q10: 0 | R10: 2 | S10: 0 | T10: 0 | U10: 0 | V10: =COUNTIF(tbl_General[EmployeeID],tbl_General[[#This Row],[EmployeeID]]) -> 1
A11: 18 | B11: No | C11: Non-Travel | D11: Research & Development | E11: 1 | F11: 4 | G11: Medical | H11: 715 | I11: Male | J11: 2 | K11: Sales Executive | L11: Single | M11: 27200 | N11: 1 | O11: 22 | P11: 1 | Q11: 0 | R11: 2 | S11: 0 | T11: 0 | U11: 0 | V11: =COUNTIF(tbl_General[EmployeeID],tbl_General[[#This Row],[EmployeeID]]) -> 1
A12: 18 | B12: No | C12: Non-Travel | D12: Research & Development | E12: 1 | F12: 4 | G12: Medical | H12: 2185 | I12: Male | J12: 2 | K12: Sales Executive | L12: Single | M12: 27200 | N12: 1 | O12: 22 | P12: 1 | Q12: 0 | R12: 2 | S12: 0 | T12: 0 | U12: 0 | V12: =COUNTIF(tbl_General[EmployeeID],tbl_General[[#This Row],[EmployeeID]]) -> 1
A13: 18 | B13: No | C13: Non-Travel | D13: Research & Development | E13: 1 | F13: 4 | G13: Medical | H13: 3655 | I13: Male | J13: 2 | K13: Sales Executive | L13: Single | M13: 27200 | N13: 1 | O13: 22 | P13: 1 | Q13: 0 | R13: 2 | S13: 0 | T13: 0 | U13: 0 | V13: =COUNTIF(tbl_General[EmployeeID],tbl_General[[#This Row],[EmployeeID]]) -> 1
... A4411: 58 | B4411: Yes | C4411: Travel_Rarely | D4411: Sales | E4411: 2 | F4411: 2 | G4411: Medical | H4411: 4279 | I4411: Female | J4411: 1 | K4411: Research Scientist | L4411: Married | M4411: 43850 | N4411: 1 | O4411: 13 | P4411: 1 | Q4411: 40 | R4411: 2 | S4411: 40 | T4411: 15 | U4411: 6 | V4411: =COUNTIF(tbl_General[EmployeeID],tbl_General[[#This Row],[EmployeeID]]) -> 1

Sheet employee_survey_data
A1: EmployeeID | B1: EnvironmentSatisfaction | C1: JobSatisfaction | D1: WorkLifeBalance | E1: ID_Check
A2: 1 | B2: 3 | C2: 4 | D2: 2 | E2: =COUNTIF(tbl_EmployeeSurvey[EmployeeID],tbl_EmployeeSurvey[[#This Row],[EmployeeID]]) -> 1
A3: 2 | B3: 3 | C3: 2 | D3: 4 | E3: =COUNTIF(tbl_EmployeeSurvey[EmployeeID],tbl_EmployeeSurvey[[#This Row],[EmployeeID]]) -> 1
A4: 3 | B4: 2 | C4: 2 | D4: 1 | E4: =COUNTIF(tbl_EmployeeSurvey[EmployeeID],tbl_EmployeeSurvey[[#This Row],[EmployeeID]]) -> 1
A5: 4 | B5: 4 | C5: 4 | D5: 3 | E5: =COUNTIF(tbl_EmployeeSurvey[EmployeeID],tbl_EmployeeSurvey[[#This Row],[EmployeeID]]) -> 1
A6: 5 | B6: 4 | C6: 1 | D6: 3 | E6: =COUNTIF(tbl_EmployeeSurvey[EmployeeID],tbl_EmployeeSurvey[[#This Row],[EmployeeID]]) -> 1
A7: 6 | B7: 3 | C7: 2 | D7: 2 | E7: =COUNTIF(tbl_EmployeeSurvey[EmployeeID],tbl_EmployeeSurvey[[#This Row],[EmployeeID]]) -> 1
A8: 7 | B8: 1 | C8: 3 | D8: 1 | E8: =COUNTIF(tbl_EmployeeSurvey[EmployeeID],tbl_EmployeeSurvey[[#This Row],[EmployeeID]]) -> 1
A9: 8 | B9: 1 | C9: 2 | D9: 3 | E9: =COUNTIF(tbl_EmployeeSurvey[EmployeeID],tbl_EmployeeSurvey[[#This Row],[EmployeeID]]) -> 1
A10: 9 | B10: 2 | C10: 4 | D10: 3 | E10: =COUNTIF(tbl_EmployeeSurvey[EmployeeID],tbl_EmployeeSurvey[[#This Row],[EmployeeID]]) -> 1
A11: 10 | B11: 2 | C11: 1 | D11: 3 | E11: =COUNTIF(tbl_EmployeeSurvey[EmployeeID],tbl_EmployeeSurvey[[#This Row],[EmployeeID]]) -> 1
A12: 11 | B12: 3 | C12: 4 | D12: 3 | E12: =COUNTIF(tbl_EmployeeSurvey[EmployeeID],tbl_EmployeeSurvey[[#This Row],[EmployeeID]]) -> 1
A13: 12 | B13: 3 | C13: 4 | D13: 3 | E13: =COUNTIF(tbl_EmployeeSurvey[EmployeeID],tbl_EmployeeSurvey[[#This Row],[EmployeeID]]) -> 1
... A4411: 4410 | B4411: 1 | C4411: 3 | D4411: 3 | E4411: =COUNTIF(tbl_EmployeeSurvey[EmployeeID],tbl_EmployeeSurvey[[#This Row],[EmployeeID]]) -> 1

Sheet manager_survey_data
A1: EmployeeID | B1: JobInvolvement | C1: PerformanceRating | D1: ID_Check
A2: 1 | B2: 3 | C2: 3 | D2: =COUNTIF(tbl_ManagerSurvey[EmployeeID],tbl_ManagerSurvey[[#This Row],[EmployeeID]]) -> 1
A3: 2 | B3: 2 | C3: 4 | D3: =COUNTIF(tbl_ManagerSurvey[EmployeeID],tbl_ManagerSurvey[[#This Row],[EmployeeID]]) -> 1
A4: 3 | B4: 3 | C4: 3 | D4: =COUNTIF(tbl_ManagerSurvey[EmployeeID],tbl_ManagerSurvey[[#This Row],[EmployeeID]]) -> 1
A5: 4 | B5: 2 | C5: 3 | D5: =COUNTIF(tbl_ManagerSurvey[EmployeeID],tbl_ManagerSurvey[[#This Row],[EmployeeID]]) -> 1
A6: 5 | B6: 3 | C6: 3 | D6: =COUNTIF(tbl_ManagerSurvey[EmployeeID],tbl_ManagerSurvey[[#This Row],[EmployeeID]]) -> 1
A7: 6 | B7: 3 | C7: 3 | D7: =COUNTIF(tbl_ManagerSurvey[EmployeeID],tbl_ManagerSurvey[[#This Row],[EmployeeID]]) -> 1
A8: 7 | B8: 3 | C8: 4 | D8: =COUNTIF(tbl_ManagerSurvey[EmployeeID],tbl_ManagerSurvey[[#This Row],[EmployeeID]]) -> 1
A9: 8 | B9: 3 | C9: 4 | D9: =COUNTIF(tbl_ManagerSurvey[EmployeeID],tbl_ManagerSurvey[[#This Row],[EmployeeID]]) -> 1
A10: 9 | B10: 3 | C10: 4 | D10: =COUNTIF(tbl_ManagerSurvey[EmployeeID],tbl_ManagerSurvey[[#This Row],[EmployeeID]]) -> 1
A11: 10 | B11: 3 | C11: 3 | D11: =COUNTIF(tbl_ManagerSurvey[EmployeeID],tbl_ManagerSurvey[[#This Row],[EmployeeID]]) -> 1
A12: 11 | B12: 2 | C12: 3 | D12: =COUNTIF(tbl_ManagerSurvey[EmployeeID],tbl_ManagerSurvey[[#This Row],[EmployeeID]]) -> 1
A13: 12 | B13: 3 | C13: 3 | D13: =COUNTIF(tbl_ManagerSurvey[EmployeeID],tbl_ManagerSurvey[[#This Row],[EmployeeID]]) -> 1
... A4411: 4410 | B4411: 4 | C4411: 3 | D4411: =COUNTIF(tbl_ManagerSurvey[EmployeeID],tbl_ManagerSurvey[[#This Row],[EmployeeID]]) -> 1

Sheet Attrition Rate by Department
A3: Row Labels | B3: Attrition Rate by Department
A4: Human Resources | B4: 0.3015873
A5: Research & Development | B5: 0.15712799
A6: Sales | B6: 0.15022422
A7: Grand Total | B7: 0.16122449

Sheet Attrition Rate by Age Group
A3: Row Labels | B3: Average of AttritionFlag
A4: Under 25 | B4: 0.39175258
A5: 25-34 | B5: 0.20216606
A6: 35-44 | B6: 0.1009901
A7: 45-54 | B7: 0.10204082
A8: Above 54 | B8: 0.15942029
A9: Grand Total | B9: 0.16122449

Sheet Attrition Rate by Tenure Group
A3: Row Labels | B3: Attrition Rate by Tenure Group
A4: < 2 Years | B4: 0.34883721
A5: 2-4 Years | B5: 0.18082192
A6: 5-9 Years | B6: 0.11068702
A7: 10+ Years | B7: 0.10382514
A8: Grand Total | B8: 0.16122449

Sheet Attrition Rate by Job Satisfact
A3: Row Labels | B3: Average of AttritionFlag
A4: 1 | B4: 0.22906977
A5: 2 | B5: 0.16428571
A6: 3 | B6: 0.16381236
A7: 4 | B7: 0.11411851
A8: Grand Total | B8: 0.16122449

Sheet Attrition Rate by WorkLifeBalan
A3: Row Labels | B3: Attrition Rate by Work-Life Balance
A4: 1 | B4: 0.31380753
A5: 2 | B5: 0.16781158
A6: 3 | B6: 0.14232765
A7: 4 | B7: 0.1784141
A8: Grand Total | B8: 0.16122449

Sheet KPI Pivot
A3: Count of EmployeeID | B3: Sum of AttritionFlag | C3: Average of AttritionFlag2 | D3: Average of MonthlyIncome | E3: Average of Age | F3: Average of YearsAtCompany
A4: 4410 | B4: 711 | C4: 0.16122449 | D4: 65029.313 | E4: 36.92381 | F4: 7.0081633
